sayhello/__init__.py
sayhello/hello.py
sayhello_world-0.0.2.dist-info/METADATA
sayhello_world-0.0.2.dist-info/WHEEL
sayhello_world-0.0.2.dist-info/top_level.txt
sayhello_world-0.0.2.dist-info/RECORD
