Metadata-Version: 2.1
Name: sayhello-world
Version: 0.0.2
Summary: Just print sayhello world
Home-page: UNKNOWN
Author: Rashed
Author-email: <rashedhsn16@gmail.com>
License: UNKNOWN
Keywords: python,sayhello,world,sockets
Platform: UNKNOWN
Classifier: Development Status :: 1 - Planning
Classifier: Intended Audience :: Developers
Classifier: Programming Language :: Python :: 3
Classifier: Operating System :: Unix
Classifier: Operating System :: MacOS :: MacOS X
Classifier: Operating System :: Microsoft :: Windows
